{"postfix": "corporate_office_properties_trus-aktie", "name": "CORPORATE_OFFICE_PROPERTIES_TRUS", "wkn": "913833", "time": "2020.05.26 16:56", "ts": 1590504967, "features": {"KGV": "17.06", "Marktkapitalisierung": {"Size": "Mrd", "Value": "2.40"}, "GA": "1.71", "KBV": "1.96", "BA": "14.87", "KCV": "18.69", "CA": "1.56", "Vola30": "50.81", "Vola90": "73.37", "Vola180": "53.31", "Vola250": "39.9"}, "rivals": [], "text_data": {"de": [["02.05.20", "Corporate Office Properties Trus gew\u00e4hrte Anlegern Blick in die B\u00fccher "], ["30.04.20", "So sch\u00e4tzen die Analysten die Corporate Office Properties Trus-Aktie im April 2020 ein"], ["29.04.20", "Ausblick: Corporate Office Properties Trus gibt Ergebnis zum abgelaufenen Quartal bekannt"], ["15.04.20", "Erste Sch\u00e4tzungen: Corporate Office Properties Trus stellt Quartalsergebnis zum abgelaufenen Jahresviertel vor"], ["29.02.20", "Corporate Office Properties Trus-Aktie: Einsch\u00e4tzungen und Kursziele der Analysten im Februar"], ["08.02.20", "Corporate Office Properties Trus stellte Ergebnisse des abgelaufenen Quartals vor"], ["05.02.20", "Ausblick: Corporate Office Properties Trus pr\u00e4sentiert Bilanzzahlen zum j\u00fcngsten Jahresviertel"]], "en": [["21.05.20", "COPT Declares 90th Consecutive Common Dividend"], ["30.04.20", "COPT Executes Build-to-Suit with Defense Contractor for 7100 Redstone Gateway"], ["30.04.20", "COPT Reports First Quarter 2020 Results"], ["21.04.20", "COPT Announces Format Change to Its 2020 Annual Meeting of Shareholders"], ["15.04.20", "COPT Adds COVID-19 Update Presentation to Website"], ["02.04.20", "COPT Announces First Quarter 2020 Earnings Conference Call"], ["01.04.20", "COPT Launches Webpage on Sustainability"], ["02.03.20", "Presentation Date/Time Updated: COPT to Present at Citi\u2019s 2020 Global Property CEO Conference"], ["27.02.20", "COPT to Present at Citi\u2019s 2020 Global Property CEO Conference"], ["25.02.20", "COPT Declares 89th Consecutive Common Dividend"], ["06.02.20", "COPT Establishes Full Year and 1Q 2020 Guidance"], ["27.01.20", "COPT Announces Tax Treatment of 2019 Distributions"], ["09.01.20", "COPT Announces Fourth Quarter and Year End 2019 Earnings Conference Call"], ["2018-09-24 20:16", "COPT Unveils New Investors WebsiteCorporate Office Properties Trust (\"COPT\" or the \"Company\") (NYSE: OFC) is pleased to announce the launch of its new Investors website: https://investors."], ["2018-07-02 12:00", "COPT Announces Second Quarter 2018 Earnings Conference CallCorporate Office Properties Trust ('COPT\" or the 'Company\") (NYSE: OFC) announces its second quarter 2018 earnings release and conf..."], ["2018-06-27 20:16", "COPT Completes Full-Building Lease of NoVA BCorporate Office Properties Trust (\"COPT\" or the \"Company\") (NYSE: OFC) has executed a full building lease with a Defense/IT tenant for 100% of ..."], ["2018-05-07 10:00", "COPT Executes Two Build-to-Suit LeasesCorporate Office Properties Trust (\"COPT\" or the \"Company\") (NYSE: OFC) executed long-term leases with a Fortune 500 company for two, 100% ..."]]}}